Metadata-Version: 2.1
Name: vmnlcli
Version: 0.2.0
Summary: command line interface for some dutch velomobile websites
Home-page: http://github.com/thomaswaldmann/velomobielnl/
Author: Thomas Waldmann
Author-email: twaldmann@thinkmo.de
License: MIT
Keywords: velomobile odometer cli velomobiel.nl intercitybike.nl welmers.net
Platform: any
Classifier: Development Status :: 4 - Beta
Classifier: Environment :: Console
Classifier: License :: OSI Approved :: MIT License
Classifier: Operating System :: OS Independent
Classifier: Programming Language :: Python
Classifier: Programming Language :: Python :: 3
Classifier: Programming Language :: Python :: 3.5
Classifier: Programming Language :: Python :: 3.6
Classifier: Programming Language :: Python :: 3.7
Classifier: Programming Language :: Python :: 3.8
Classifier: Topic :: Utilities
Classifier: Topic :: Database :: Front-Ends
Classifier: Topic :: Internet :: WWW/HTTP :: Site Management
Requires-Python: >=3.5
